bm25_parallel-0.1.0.dist-info/METADATA
bm25_parallel-0.1.0.dist-info/WHEEL
bm25_parallel/__init__.py
bm25_parallel/bm25_parallel.cp312-win_amd64.pyd
bm25_parallel-0.1.0.dist-info/RECORD
