Metadata-Version: 2.4
Name: bm25-parallel
Version: 0.1.0
Classifier: Programming Language :: Python :: 3
Classifier: Programming Language :: Rust
Classifier: License :: OSI Approved :: MIT License
Classifier: Operating System :: OS Independent
Summary: Rust-accelerated BM25 search with Rayon
Keywords: bm25,search,rust,rayon
Author-email: Your Name <you@example.com>
License: MIT
Requires-Python: >=3.8
Project-URL: Homepage, https://github.com/yourname/bm25_parallel
Project-URL: Repository, https://github.com/yourname/bm25_parallel
